googleaudio/__init__.py
googleaudio/colabaudio.py
GoogleAudio-0.0.3.dist-info/METADATA
GoogleAudio-0.0.3.dist-info/WHEEL
GoogleAudio-0.0.3.dist-info/top_level.txt
GoogleAudio-0.0.3.dist-info/RECORD
