Metadata-Version: 2.1
Name: GoogleAudio
Version: 0.0.3
Summary: Google Colab Microphone Audio Recoring Package
Home-page: https://github.com/falahgs/
Author: Falahgs.G.Saleih
Author-email: falahgs07@gmail.com
License: MIT
Keywords: Google Colab,Audio,Wav file
Classifier: Programming Language :: Python :: 3
Classifier: License :: OSI Approved :: MIT License
Classifier: Operating System :: OS Independent
Requires-Python: >=3.6
Requires-Dist: ffmpeg-python
